plover_regenpfeifer/__init__.py
plover_regenpfeifer/system.py
plover_regenpfeifer/dictionaries/regenpfeifer_main.json
plover_regenpfeifer-1.1.2.dist-info/LICENSE
plover_regenpfeifer-1.1.2.dist-info/METADATA
plover_regenpfeifer-1.1.2.dist-info/WHEEL
plover_regenpfeifer-1.1.2.dist-info/entry_points.txt
plover_regenpfeifer-1.1.2.dist-info/top_level.txt
plover_regenpfeifer-1.1.2.dist-info/zip-safe
plover_regenpfeifer-1.1.2.dist-info/RECORD
