Metadata-Version: 2.1
Name: plover_regenpfeifer
Version: 1.1.2
Summary: German realtime system for Plover
Home-page: https://github.com/mkrnr/plover_regenpfeifer
Author: Martin Koerner
Author-email: info@mkoerner.de
License: GNU General Public License v3 or later (GPLv3+)
Keywords: plover plover_plugin
Classifier: Development Status :: 4 - Beta
Classifier: Environment :: Plugins
Classifier: Intended Audience :: End Users/Desktop
Classifier: License :: OSI Approved :: GNU General Public License v2 or later (GPLv2+)
Classifier: Operating System :: OS Independent
Classifier: Programming Language :: Python :: 3
Classifier: Programming Language :: Python :: 3.6
License-File: LICENSE
Requires-Dist: plover>=4.0.0.dev1
